{
  "minecraft:recipes/tools/stone_shovel": {
    "criteria": {
      "has_cobblestone": "2024-01-27 23:48:52 +0300"
    },
    "done": true
  },
  "minecraft:recipes/building_blocks/cobblestone_slab_from_cobblestone_stonecutting": {
    "criteria": {
      "has_cobblestone": "2024-01-27 23:48:52 +0300"
    },
    "done": true
  },
  "minecraft:recipes/tools/stone_hoe": {
    "criteria": {
      "has_cobblestone": "2024-01-27 23:48:52 +0300"
    },
    "done": true
  },
  "minecraft:recipes/redstone/lever": {
    "criteria": {
      "has_cobblestone": "2024-01-27 23:48:52 +0300"
    },
    "done": true
  },
  "minecraft:recipes/building_blocks/cobblestone_stairs_from_cobblestone_stonecutting": {
    "criteria": {
      "has_cobblestone": "2024-01-27 23:48:52 +0300"
    },
    "done": true
  },
  "minecraft:recipes/combat/stone_sword": {
    "criteria": {
      "has_cobblestone": "2024-01-27 23:48:52 +0300"
    },
    "done": true
  },
  "minecraft:recipes/decorations/cobblestone_wall": {
    "criteria": {
      "has_cobblestone": "2024-01-27 23:48:52 +0300"
    },
    "done": true
  },
  "minecraft:recipes/tools/stone_pickaxe": {
    "criteria": {
      "has_cobblestone": "2024-01-27 23:48:52 +0300"
    },
    "done": true
  },
  "minecraft:recipes/tools/stone_axe": {
    "criteria": {
      "has_cobblestone": "2024-01-27 23:48:52 +0300"
    },
    "done": true
  },
  "minecraft:story/mine_stone": {
    "criteria": {
      "get_stone": "2024-01-27 23:48:52 +0300"
    },
    "done": true
  },
  "minecraft:recipes/building_blocks/stone": {
    "criteria": {
      "has_cobblestone": "2024-01-27 23:48:52 +0300"
    },
    "done": true
  },
  "minecraft:recipes/building_blocks/cobblestone_slab": {
    "criteria": {
      "has_cobblestone": "2024-01-27 23:48:52 +0300"
    },
    "done": true
  },
  "minecraft:recipes/decorations/furnace": {
    "criteria": {
      "has_cobblestone": "2024-01-27 23:48:52 +0300"
    },
    "done": true
  },
  "minecraft:recipes/decorations/cobblestone_wall_from_cobblestone_stonecutting": {
    "criteria": {
      "has_cobblestone": "2024-01-27 23:48:52 +0300"
    },
    "done": true
  },
  "minecraft:adventure/adventuring_time": {
    "criteria": {
      "minecraft:frozen_river": "2024-01-27 23:39:52 +0300",
      "minecraft:snowy_plains": "2024-01-27 23:39:14 +0300",
      "minecraft:snowy_taiga": "2024-01-27 23:39:34 +0300",
      "minecraft:ice_spikes": "2024-01-27 23:42:18 +0300",
      "minecraft:plains": "2024-01-27 23:49:09 +0300"
    },
    "done": false
  },
  "minecraft:recipes/building_blocks/cobblestone_stairs": {
    "criteria": {
      "has_cobblestone": "2024-01-27 23:48:52 +0300"
    },
    "done": true
  },
  "DataVersion": 3120
}